pyrfc/__init__.py
pyrfc/_cyrfc.cp311-win_amd64.pdb
pyrfc/_cyrfc.cp311-win_amd64.pyd
pyrfc/_exception.py
pyrfc/_utils.py
pyrfc-3.3.1.dist-info/Apache-2.0.txt
pyrfc-3.3.1.dist-info/METADATA
pyrfc-3.3.1.dist-info/WHEEL
pyrfc-3.3.1.dist-info/top_level.txt
pyrfc-3.3.1.dist-info/RECORD
