Metadata-Version: 2.1
Name: pyrfc
Version: 3.3.1
Summary: Python bindings for SAP NetWeaver RFC SDK
Author: SAP SE
Author-email: srdjan.boskovic@sap.com
Maintainer-email: Srdjan Boskovic <srdjan.boskovic@sap.com>
License:                                  Apache License
Project-URL: bug-tracker, https://github.com/wntrblm/nox/issues
Project-URL: documentation, http://sap.github.io/PyRFC
Project-URL: homepage, https://github.com/SAP/PyRFC
Project-URL: repository, https://github.com/SAP/PyRFC.git
Keywords: pyrfc,sap,nwrfc,sapnwrfc,abap
Classifier: Topic :: Software Development :: Build Tools
Classifier: Topic :: Software Development :: Libraries :: Python Modules
Classifier: Development Status :: 5 - Production/Stable
Classifier: Intended Audience :: Developers
Classifier: Natural Language :: English
Classifier: License :: OSI Approved :: Apache Software License
Classifier: Operating System :: OS Independent
Classifier: Programming Language :: Cython
Classifier: Programming Language :: Python
Classifier: Programming Language :: Python :: 3.8
Classifier: Programming Language :: Python :: 3.9
Classifier: Programming Language :: Python :: 3.10
Classifier: Programming Language :: Python :: 3.11
Classifier: Programming Language :: Python :: 3.12
Classifier: Programming Language :: Python :: 3 :: Only
Requires-Python: >=3.8
License-File: LICENSES/Apache-2.0.txt
